Workbook

Sheet Dashboard
A1: STEEL SECTOR: CARBON RISK & INVESTMENT STRATEGY (2030)
B4: Portfolio EBITDA ($B) | D4: Avg. Margin Erosion | F4: Total Carbon Cost ($B) | H4: High-Risk Assets
B5: =SUM('[1]Company Data & Assumptions'!$H$2:$H$11) -> 48.4 | D5: =F5/B5 -> 0.69513099 | F5: =SUM('[1]Carbon Risk Engine'!$H$2:$H$11) -> 33.64434 | H5: =COUNTIF('[1]Investment Thesis'!$D$2:$D$11, "SELL") / COUNTA('[1]Investment Thesis'!$A$2:$A$11) -> 0.4
I21: Company | J21: Base EBITDA ($B) | K21: Domestic Carbon Cost ($B) | L21: Stress Erosion %
I22: ='[1]Company Data & Assumptions'!A2 -> Nucor | J22: ='[1]Company Data & Assumptions'!H2 -> 5.3 | K22: ='[1]Carbon Risk Engine'!G2 -> 0.4515 | L22: ='[1]Carbon Risk Engine'!S2 -> 0.11415094
I23: ='[1]Company Data & Assumptions'!A3 -> Steel Dynamics | J23: ='[1]Company Data & Assumptions'!H3 -> 3.5 | K23: ='[1]Carbon Risk Engine'!G3 -> 0.273 | L23: ='[1]Carbon Risk Engine'!S3 -> 0.1
I24: ='[1]Company Data & Assumptions'!A4 -> ArcelorMittal | J24: ='[1]Company Data & Assumptions'!H4 -> 6.5 | K24: ='[1]Carbon Risk Engine'!G4 -> 4.263 | L24: ='[1]Carbon Risk Engine'!S4 -> 0.93076923
I25: ='[1]Company Data & Assumptions'!A5 -> Baowu Steel | J25: ='[1]Company Data & Assumptions'!H5 -> 12 | K25: ='[1]Carbon Risk Engine'!G5 -> 11.466 | L25: ='[1]Carbon Risk Engine'!S5 -> 1.3616667
I26: ='[1]Company Data & Assumptions'!A6 -> POSCO | J26: ='[1]Company Data & Assumptions'!H6 -> 5.5 | K26: ='[1]Carbon Risk Engine'!G6 -> 3.4398 | L26: ='[1]Carbon Risk Engine'!S6 -> 0.88618182
I27: ='[1]Company Data & Assumptions'!A7 -> Nippon Steel | J27: ='[1]Company Data & Assumptions'!H7 -> 5 | K27: ='[1]Carbon Risk Engine'!G7 -> 3.7884 | L27: ='[1]Carbon Risk Engine'!S7 -> 1.0744
I28: ='[1]Company Data & Assumptions'!A8 -> Tata Steel | J28: ='[1]Company Data & Assumptions'!H8 -> 3.1 | K28: ='[1]Carbon Risk Engine'!G8 -> 2.89044 | L28: ='[1]Carbon Risk Engine'!S8 -> 1.3190968
I29: ='[1]Company Data & Assumptions'!A9 -> JSW Steel | J29: ='[1]Company Data & Assumptions'!H9 -> 2.8 | K29: ='[1]Carbon Risk Engine'!G9 -> 2.7636 | L29: ='[1]Carbon Risk Engine'!S9 -> 1.3957143
I30: ='[1]Company Data & Assumptions'!A10 -> Thyssenkrupp | J30: ='[1]Company Data & Assumptions'!H10 -> 2.5 | K30: ='[1]Carbon Risk Engine'!G10 -> 0.9933 | L30: ='[1]Carbon Risk Engine'!S10 -> 0.5516
I31: ='[1]Company Data & Assumptions'!A11 -> Voestalpine | J31: ='[1]Company Data & Assumptions'!H11 -> 2.2 | K31: ='[1]Carbon Risk Engine'!G11 -> 0.4704 | L31: ='[1]Carbon Risk Engine'!S11 -> 0.28727273
A69: STRATEGIC FINDING: The global steel sector is facing a "Margin Cliff." Companies relying on Coal-based (BF-BOF) production face 100%+ margin erosion by 2030 unless they deploy massive Green Hydrogen/EAF capex. We recommend an Overweight position on US-based scrap recyclers (Nucor/SDI) and a Sell on high-intensity Asian producers.

Sheet DashboardData
A1: Company | B1: Region | C1: Scenario | D1: Adj. EBITDA | E1: Erosion % | F1: Net Compliance Cost ($B) | G1: ESG Rating
A2: =Company_Data!A2 -> Nucor | B2: =Company_Data!B2 -> USA | C2: Base Case | D2: =VLOOKUP(A2, Valuation_Impact!A:B, 2, FALSE) -> 5.1495 | E2: =VLOOKUP(A2, Valuation_Impact!A:C, 3, FALSE) -> 0.028396226 | F2: =Carbon_Risk_Engine!H2 -> 0.4515 | G2: =Valuation_Impact!F2 -> AAA
A3: =Company_Data!A3 -> Steel Dynamics | B3: =Company_Data!B3 -> USA | C3: Base Case | D3: =VLOOKUP(A3, Valuation_Impact!A:B, 2, FALSE) -> 3.409 | E3: =VLOOKUP(A3, Valuation_Impact!A:C, 3, FALSE) -> 0.026 | F3: =Carbon_Risk_Engine!H3 -> 0.273 | G3: =Valuation_Impact!F3 -> AAA
A4: =Company_Data!A4 -> ArcelorMittal | B4: =Company_Data!B4 -> Europe/Global | C4: Base Case | D4: =VLOOKUP(A4, Valuation_Impact!A:B, 2, FALSE) -> 4.6065 | E4: =VLOOKUP(A4, Valuation_Impact!A:C, 3, FALSE) -> 0.29130769 | F4: =Carbon_Risk_Engine!H4 -> 4.7355 | G4: =Valuation_Impact!F4 -> BBB
A5: =Company_Data!A5 -> Baowu Steel | B5: =Company_Data!B5 -> China | C5: Base Case | D5: =VLOOKUP(A5, Valuation_Impact!A:B, 2, FALSE) -> 7.548 | E5: =VLOOKUP(A5, Valuation_Impact!A:C, 3, FALSE) -> 0.371 | F5: =Carbon_Risk_Engine!H5 -> 12.096 | G5: =Valuation_Impact!F5 -> CCC
A6: =Company_Data!A6 -> POSCO | B6: =Company_Data!B6 -> South Korea | C6: Base Case | D6: =VLOOKUP(A6, Valuation_Impact!A:B, 2, FALSE) -> 4.1059 | E6: =VLOOKUP(A6, Valuation_Impact!A:C, 3, FALSE) -> 0.25347273 | F6: =Carbon_Risk_Engine!H6 -> 3.6873 | G6: =Valuation_Impact!F6 -> BBB
A7: =Company_Data!A7 -> Nippon Steel | B7: =Company_Data!B7 -> Japan | C7: Base Case | D7: =VLOOKUP(A7, Valuation_Impact!A:B, 2, FALSE) -> 3.5032 | E7: =VLOOKUP(A7, Valuation_Impact!A:C, 3, FALSE) -> 0.29936 | F7: =Carbon_Risk_Engine!H7 -> 4.0224 | G7: =Valuation_Impact!F7 -> BBB
A8: =Company_Data!A8 -> Tata Steel | B8: =Company_Data!B8 -> India | C8: Base Case | D8: =VLOOKUP(A8, Valuation_Impact!A:B, 2, FALSE) -> 1.91512 | E8: =VLOOKUP(A8, Valuation_Impact!A:C, 3, FALSE) -> 0.38221935 | F8: =Carbon_Risk_Engine!H8 -> 3.11184 | G8: =Valuation_Impact!F8 -> CCC
A9: =Company_Data!A9 -> JSW Steel | B9: =Company_Data!B9 -> India | C9: Base Case | D9: =VLOOKUP(A9, Valuation_Impact!A:B, 2, FALSE) -> 1.7078 | E9: =VLOOKUP(A9, Valuation_Impact!A:C, 3, FALSE) -> 0.39007143 | F9: =Carbon_Risk_Engine!H9 -> 2.9346 | G9: =Valuation_Impact!F9 -> CCC
A10: =Company_Data!A10 -> Thyssenkrupp | B10: =Company_Data!B10 -> Germany | C10: Base Case | D10: =VLOOKUP(A10, Valuation_Impact!A:B, 2, FALSE) -> 1.4264 | E10: =VLOOKUP(A10, Valuation_Impact!A:C, 3, FALSE) -> 0.42944 | F10: =Carbon_Risk_Engine!H10 -> 1.7358 | G10: =Valuation_Impact!F10 -> CCC
A11: =Company_Data!A11 -> Voestalpine | B11: =Company_Data!B11 -> Austria | C11: Base Case | D11: =VLOOKUP(A11, Valuation_Impact!A:B, 2, FALSE) -> 1.9172 | E11: =VLOOKUP(A11, Valuation_Impact!A:C, 3, FALSE) -> 0.12854545 | F11: =Carbon_Risk_Engine!H11 -> 0.5964 | G11: =Valuation_Impact!F11 -> AAA
A12: =Company_Data!A2 -> Nucor | B12: =Company_Data!B2 -> USA | C12: Stress Case | D12: =VLOOKUP(A12, Stress_Scenario!A:F, 6, FALSE) -> 4.695 | E12: =VLOOKUP(A12, Stress_Scenario!A:G, 7, FALSE) -> 0.11415094 | F12: =VLOOKUP(A12, Stress_Scenario!A:E, 5, FALSE) -> 0.605 | G12: CCC
A13: =Company_Data!A3 -> Steel Dynamics | B13: =Company_Data!B3 -> USA | C13: Stress Case | D13: =VLOOKUP(A13, Stress_Scenario!A:F, 6, FALSE) -> 3.15 | E13: =VLOOKUP(A13, Stress_Scenario!A:G, 7, FALSE) -> 0.1 | F13: =VLOOKUP(A13, Stress_Scenario!A:E, 5, FALSE) -> 0.35 | G13: CCC
A14: =Company_Data!A4 -> ArcelorMittal | B14: =Company_Data!B4 -> Europe/Global | C14: Stress Case | D14: =VLOOKUP(A14, Stress_Scenario!A:F, 6, FALSE) -> 0.45 | E14: =VLOOKUP(A14, Stress_Scenario!A:G, 7, FALSE) -> 0.93076923 | F14: =VLOOKUP(A14, Stress_Scenario!A:E, 5, FALSE) -> 6.05 | G14: CCC
A15: =Company_Data!A5 -> Baowu Steel | B15: =Company_Data!B5 -> China | C15: Stress Case | D15: =VLOOKUP(A15, Stress_Scenario!A:F, 6, FALSE) -> -4.34 | E15: =VLOOKUP(A15, Stress_Scenario!A:G, 7, FALSE) -> 1.3616667 | F15: =VLOOKUP(A15, Stress_Scenario!A:E, 5, FALSE) -> 16.34 | G15: CCC
A16: =Company_Data!A6 -> POSCO | B16: =Company_Data!B6 -> South Korea | C16: Stress Case | D16: =VLOOKUP(A16, Stress_Scenario!A:F, 6, FALSE) -> 0.626 | E16: =VLOOKUP(A16, Stress_Scenario!A:G, 7, FALSE) -> 0.88618182 | F16: =VLOOKUP(A16, Stress_Scenario!A:E, 5, FALSE) -> 4.874 | G16: CCC
A17: =Company_Data!A7 -> Nippon Steel | B17: =Company_Data!B7 -> Japan | C17: Stress Case | D17: =VLOOKUP(A17, Stress_Scenario!A:F, 6, FALSE) -> -0.372 | E17: =VLOOKUP(A17, Stress_Scenario!A:G, 7, FALSE) -> 1.0744 | F17: =VLOOKUP(A17, Stress_Scenario!A:E, 5, FALSE) -> 5.372 | G17: CCC
A18: =Company_Data!A8 -> Tata Steel | B18: =Company_Data!B8 -> India | C18: Stress Case | D18: =VLOOKUP(A18, Stress_Scenario!A:F, 6, FALSE) -> -0.9892 | E18: =VLOOKUP(A18, Stress_Scenario!A:G, 7, FALSE) -> 1.3190968 | F18: =VLOOKUP(A18, Stress_Scenario!A:E, 5, FALSE) -> 4.0892 | G18: CCC
A19: =Company_Data!A9 -> JSW Steel | B19: =Company_Data!B9 -> India | C19: Stress Case | D19: =VLOOKUP(A19, Stress_Scenario!A:F, 6, FALSE) -> -1.108 | E19: =VLOOKUP(A19, Stress_Scenario!A:G, 7, FALSE) -> 1.3957143 | F19: =VLOOKUP(A19, Stress_Scenario!A:E, 5, FALSE) -> 3.908 | G19: CCC
A20: =Company_Data!A10 -> Thyssenkrupp | B20: =Company_Data!B10 -> Germany | C20: Stress Case | D20: =VLOOKUP(A20, Stress_Scenario!A:F, 6, FALSE) -> 1.121 | E20: =VLOOKUP(A20, Stress_Scenario!A:G, 7, FALSE) -> 0.5516 | F20: =VLOOKUP(A20, Stress_Scenario!A:E, 5, FALSE) -> 1.379 | G20: CCC
A21: =Company_Data!A11 -> Voestalpine | B21: =Company_Data!B11 -> Austria | C21: Stress Case | D21: =VLOOKUP(A21, Stress_Scenario!A:F, 6, FALSE) -> 1.568 | E21: =VLOOKUP(A21, Stress_Scenario!A:G, 7, FALSE) -> 0.28727273 | F21: =VLOOKUP(A21, Stress_Scenario!A:E, 5, FALSE) -> 0.632 | G21: CCC

Sheet README

Sheet Investment Recommendation
A1: =Company_Data!A1 -> Company | B1: =Company_Data!B1 -> Region | C1: =Valuation_Impact!F1 -> ESG Rating | D1: =Valuation_Impact!G1 -> Investment Rec. | E1: Professional Investment Thesis
A2: =Company_Data!A2 -> Nucor | B2: =Company_Data!B2 -> USA | C2: =Valuation_Impact!F2 -> AAA | D2: =Valuation_Impact!G2 -> BUY | E2: Primary beneficiary of the low-carbon transition. With a 100% EAF share and best-in-class intensity (0.43 tCO2/t), Nucor is effectively 'future-proofed' against carbon taxes, allowing for significant market share capture as competitors' margins erode.
A3: =Company_Data!A3 -> Steel Dynamics | B3: =Company_Data!B3 -> USA | C3: =Valuation_Impact!F3 -> AAA | D3: =Valuation_Impact!G3 -> BUY | E3: Primary beneficiary of the low-carbon transition. With a 100% EAF share and best-in-class intensity (0.5 tCO2/t), Steel Dynamics is effectively 'future-proofed' against carbon taxes, allowing for significant market share capture as competitors' margins erode.
A4: =Company_Data!A4 -> ArcelorMittal | B4: =Company_Data!B4 -> Europe/Global | C4: =Valuation_Impact!F4 -> BBB | D4: =Valuation_Impact!G4 -> HOLD | E4: Operational efficiency is high, but heavy reliance on traditional BF-BOF routes in Europe/Global creates a transition bottleneck. While currently stable, ArcelorMittal requires an estimated $34.8B in green capex to avoid long-term structural margin compression (> 29.1%).
A5: =Company_Data!A5 -> Baowu Steel | B5: =Company_Data!B5 -> China | C5: =Valuation_Impact!F5 -> CCC | D5: =Valuation_Impact!G5 -> SELL | E5: High-risk exposure to intensifying carbon regulations. With a carbon intensity of 2.1 tCO2/t, Baowu Steel faces a terminal threat to profitability, with base-case margin erosion exceeding 37.1%. The lack of aggressive H2-DRI transition plans makes the current valuation unsustainable.
A6: =Company_Data!A6 -> POSCO | B6: =Company_Data!B6 -> South Korea | C6: =Valuation_Impact!F6 -> BBB | D6: =Valuation_Impact!G6 -> HOLD | E6: Operational efficiency is high, but heavy reliance on traditional BF-BOF routes in South Korea creates a transition bottleneck. While currently stable, POSCO requires an estimated $25.2B in green capex to avoid long-term structural margin compression (> 25.3%).
A7: =Company_Data!A7 -> Nippon Steel | B7: =Company_Data!B7 -> Japan | C7: =Valuation_Impact!F7 -> BBB | D7: =Valuation_Impact!G7 -> HOLD | E7: Operational efficiency is high, but heavy reliance on traditional BF-BOF routes in Japan creates a transition bottleneck. While currently stable, Nippon Steel requires an estimated $26.4B in green capex to avoid long-term structural margin compression (> 29.9%).
A8: =Company_Data!A8 -> Tata Steel | B8: =Company_Data!B8 -> India | C8: =Valuation_Impact!F8 -> CCC | D8: =Valuation_Impact!G8 -> SELL | E8: High-risk exposure to intensifying carbon regulations. With a carbon intensity of 2.22 tCO2/t, Tata Steel faces a terminal threat to profitability, with base-case margin erosion exceeding 38.2%. The lack of aggressive H2-DRI transition plans makes the current valuation unsustainable.
A9: =Company_Data!A9 -> JSW Steel | B9: =Company_Data!B9 -> India | C9: =Valuation_Impact!F9 -> CCC | D9: =Valuation_Impact!G9 -> SELL | E9: High-risk exposure to intensifying carbon regulations. With a carbon intensity of 2.35 tCO2/t, JSW Steel faces a terminal threat to profitability, with base-case margin erosion exceeding 39.0%. The lack of aggressive H2-DRI transition plans makes the current valuation unsustainable.
A10: =Company_Data!A10 -> Thyssenkrupp | B10: =Company_Data!B10 -> Germany | C10: =Valuation_Impact!F10 -> CCC | D10: =Valuation_Impact!G10 -> SELL | E10: High-risk exposure to intensifying carbon regulations. With a carbon intensity of 2.15 tCO2/t, Thyssenkrupp faces a terminal threat to profitability, with base-case margin erosion exceeding 42.9%. The lack of aggressive H2-DRI transition plans makes the current valuation unsustainable.
A11: =Company_Data!A11 -> Voestalpine | B11: =Company_Data!B11 -> Austria | C11: =Valuation_Impact!F11 -> AAA | D11: =Valuation_Impact!G11 -> BUY | E11: Primary beneficiary of the low-carbon transition. With a 10% EAF share and best-in-class intensity (1.6 tCO2/t), Voestalpine is effectively 'future-proofed' against carbon taxes, allowing for significant market share capture as competitors' margins erode.

Sheet Stress_Scenario
A1: =Company_Data!A1 -> Company | B1: Steel Cost Cost ($B) | C1: Pass-through ($B) | D1: Stress Mitigation ($B) | E1: Stress Compliance Cost ($B) | F1: Stress Adjusted EBITDA | G1: Stress Erosion %
A2: =Company_Data!A2 -> Nucor | B2: =(Carbon_Risk_Engine!B2 * 100) / 1000 -> 1.075 | C2: =B2 * 0.4 -> 0.43 | D2: =B2 * 0.4/ B2 * 0.1 -> 0.04 | E2: =B2 - C2 - D2 -> 0.605 | F2: =Company_Data!H2 - E2 -> 4.695 | G2: =E2 / Company_Data!H2 -> 0.11415094
A3: =Company_Data!A3 -> Steel Dynamics | B3: =(Carbon_Risk_Engine!B3 * 100) / 1000 -> 0.65 | C3: =B3 * 0.4 -> 0.26 | D3: =B3 * 0.4/ B3 * 0.1 -> 0.04 | E3: =B3 - C3 - D3 -> 0.35 | F3: =Company_Data!H3 - E3 -> 3.15 | G3: =E3 / Company_Data!H3 -> 0.1
A4: =Company_Data!A4 -> ArcelorMittal | B4: =(Carbon_Risk_Engine!B4 * 100) / 1000 -> 10.15 | C4: =B4 * 0.4 -> 4.06 | D4: =B4 * 0.4/ B4 * 0.1 -> 0.04 | E4: =B4 - C4 - D4 -> 6.05 | F4: =Company_Data!H4 - E4 -> 0.45 | G4: =E4 / Company_Data!H4 -> 0.93076923
A5: =Company_Data!A5 -> Baowu Steel | B5: =(Carbon_Risk_Engine!B5 * 100) / 1000 -> 27.3 | C5: =B5 * 0.4 -> 10.92 | D5: =B5 * 0.4/ B5 * 0.1 -> 0.04 | E5: =B5 - C5 - D5 -> 16.34 | F5: =Company_Data!H5 - E5 -> -4.34 | G5: =E5 / Company_Data!H5 -> 1.3616667
A6: =Company_Data!A6 -> POSCO | B6: =(Carbon_Risk_Engine!B6 * 100) / 1000 -> 8.19 | C6: =B6 * 0.4 -> 3.276 | D6: =B6 * 0.4/ B6 * 0.1 -> 0.04 | E6: =B6 - C6 - D6 -> 4.874 | F6: =Company_Data!H6 - E6 -> 0.626 | G6: =E6 / Company_Data!H6 -> 0.88618182
A7: =Company_Data!A7 -> Nippon Steel | B7: =(Carbon_Risk_Engine!B7 * 100) / 1000 -> 9.02 | C7: =B7 * 0.4 -> 3.608 | D7: =B7 * 0.4/ B7 * 0.1 -> 0.04 | E7: =B7 - C7 - D7 -> 5.372 | F7: =Company_Data!H7 - E7 -> -0.372 | G7: =E7 / Company_Data!H7 -> 1.0744
A8: =Company_Data!A8 -> Tata Steel | B8: =(Carbon_Risk_Engine!B8 * 100) / 1000 -> 6.882 | C8: =B8 * 0.4 -> 2.7528 | D8: =B8 * 0.4/ B8 * 0.1 -> 0.04 | E8: =B8 - C8 - D8 -> 4.0892 | F8: =Company_Data!H8 - E8 -> -0.9892 | G8: =E8 / Company_Data!H8 -> 1.3190968
A9: =Company_Data!A9 -> JSW Steel | B9: =(Carbon_Risk_Engine!B9 * 100) / 1000 -> 6.58 | C9: =B9 * 0.4 -> 2.632 | D9: =B9 * 0.4/ B9 * 0.1 -> 0.04 | E9: =B9 - C9 - D9 -> 3.908 | F9: =Company_Data!H9 - E9 -> -1.108 | G9: =E9 / Company_Data!H9 -> 1.3957143
A10: =Company_Data!A10 -> Thyssenkrupp | B10: =(Carbon_Risk_Engine!B10 * 100) / 1000 -> 2.365 | C10: =B10 * 0.4 -> 0.946 | D10: =B10 * 0.4/ B10 * 0.1 -> 0.04 | E10: =B10 - C10 - D10 -> 1.379 | F10: =Company_Data!H10 - E10 -> 1.121 | G10: =E10 / Company_Data!H10 -> 0.5516
A11: =Company_Data!A11 -> Voestalpine | B11: =(Carbon_Risk_Engine!B11 * 100) / 1000 -> 1.12 | C11: =B11 * 0.4 -> 0.448 | D11: =B11 * 0.4/ B11 * 0.1 -> 0.04 | E11: =B11 - C11 - D11 -> 0.632 | F11: =Company_Data!H11 - E11 -> 1.568 | G11: =E11 / Company_Data!H11 -> 0.28727273

Sheet Valuation_Impact
A1: =Company_Data!A1 -> Company | B1: Adjusted EBITDA | C1: Margin Erosion % | D1: Transition Capex Requried | E1: Strategic Outlook | F1: ESG Rating | G1: Investment Rec.
A2: =Company_Data!A2 -> Nucor | B2: =Company_Data!H2 - Carbon_Risk_Engine!J2 -> 5.1495 | C2: =IF(B2 <= 0, "EBITDA Negative", (Company_Data!H2 - B2) / Company_Data!H2) -> 0.028396226 | D2: =(Company_Data!C2 * Assumptions!$B$8)/1000 -> 15 | E2: =IF(C2 < 0.15, "LEADER", IF(C2 < 0.4, "STABLE", "AT RISK")) -> LEADER | F2: =IF(C2 < 0.15, "AAA", IF(C2 < 0.35, "BBB", "CCC")) -> AAA | G2: =IF(F2 = "AAA", "BUY", IF(F2 = "BBB", "HOLD", "SELL")) -> BUY
A3: =Company_Data!A3 -> Steel Dynamics | B3: =Company_Data!H3 - Carbon_Risk_Engine!J3 -> 3.409 | C3: =IF(B3 <= 0, "EBITDA Negative", (Company_Data!H3 - B3) / Company_Data!H3) -> 0.026 | D3: =(Company_Data!C3 * Assumptions!$B$8)/1000 -> 7.8 | E3: =IF(C3 < 0.15, "LEADER", IF(C3 < 0.4, "STABLE", "AT RISK")) -> LEADER | F3: =IF(C3 < 0.15, "AAA", IF(C3 < 0.35, "BBB", "CCC")) -> AAA | G3: =IF(F3 = "AAA", "BUY", IF(F3 = "BBB", "HOLD", "SELL")) -> BUY
A4: =Company_Data!A4 -> ArcelorMittal | B4: =Company_Data!H4 - Carbon_Risk_Engine!J4 -> 4.6065 | C4: =IF(B4 <= 0, "EBITDA Negative", (Company_Data!H4 - B4) / Company_Data!H4) -> 0.29130769 | D4: =(Company_Data!C4 * Assumptions!$B$8)/1000 -> 34.8 | E4: =IF(C4 < 0.15, "LEADER", IF(C4 < 0.4, "STABLE", "AT RISK")) -> STABLE | F4: =IF(C4 < 0.15, "AAA", IF(C4 < 0.35, "BBB", "CCC")) -> BBB | G4: =IF(F4 = "AAA", "BUY", IF(F4 = "BBB", "HOLD", "SELL")) -> HOLD
A5: =Company_Data!A5 -> Baowu Steel | B5: =Company_Data!H5 - Carbon_Risk_Engine!J5 -> 7.548 | C5: =IF(B5 <= 0, "EBITDA Negative", (Company_Data!H5 - B5) / Company_Data!H5) -> 0.371 | D5: =(Company_Data!C5 * Assumptions!$B$8)/1000 -> 78 | E5: =IF(C5 < 0.15, "LEADER", IF(C5 < 0.4, "STABLE", "AT RISK")) -> STABLE | F5: =IF(C5 < 0.15, "AAA", IF(C5 < 0.35, "BBB", "CCC")) -> CCC | G5: =IF(F5 = "AAA", "BUY", IF(F5 = "BBB", "HOLD", "SELL")) -> SELL
A6: =Company_Data!A6 -> POSCO | B6: =Company_Data!H6 - Carbon_Risk_Engine!J6 -> 4.1059 | C6: =IF(B6 <= 0, "EBITDA Negative", (Company_Data!H6 - B6) / Company_Data!H6) -> 0.25347273 | D6: =(Company_Data!C6 * Assumptions!$B$8)/1000 -> 25.2 | E6: =IF(C6 < 0.15, "LEADER", IF(C6 < 0.4, "STABLE", "AT RISK")) -> STABLE | F6: =IF(C6 < 0.15, "AAA", IF(C6 < 0.35, "BBB", "CCC")) -> BBB | G6: =IF(F6 = "AAA", "BUY", IF(F6 = "BBB", "HOLD", "SELL")) -> HOLD
A7: =Company_Data!A7 -> Nippon Steel | B7: =Company_Data!H7 - Carbon_Risk_Engine!J7 -> 3.5032 | C7: =IF(B7 <= 0, "EBITDA Negative", (Company_Data!H7 - B7) / Company_Data!H7) -> 0.29936 | D7: =(Company_Data!C7 * Assumptions!$B$8)/1000 -> 26.4 | E7: =IF(C7 < 0.15, "LEADER", IF(C7 < 0.4, "STABLE", "AT RISK")) -> STABLE | F7: =IF(C7 < 0.15, "AAA", IF(C7 < 0.35, "BBB", "CCC")) -> BBB | G7: =IF(F7 = "AAA", "BUY", IF(F7 = "BBB", "HOLD", "SELL")) -> HOLD
A8: =Company_Data!A8 -> Tata Steel | B8: =Company_Data!H8 - Carbon_Risk_Engine!J8 -> 1.91512 | C8: =IF(B8 <= 0, "EBITDA Negative", (Company_Data!H8 - B8) / Company_Data!H8) -> 0.38221935 | D8: =(Company_Data!C8 * Assumptions!$B$8)/1000 -> 18.6 | E8: =IF(C8 < 0.15, "LEADER", IF(C8 < 0.4, "STABLE", "AT RISK")) -> STABLE | F8: =IF(C8 < 0.15, "AAA", IF(C8 < 0.35, "BBB", "CCC")) -> CCC | G8: =IF(F8 = "AAA", "BUY", IF(F8 = "BBB", "HOLD", "SELL")) -> SELL
A9: =Company_Data!A9 -> JSW Steel | B9: =Company_Data!H9 - Carbon_Risk_Engine!J9 -> 1.7078 | C9: =IF(B9 <= 0, "EBITDA Negative", (Company_Data!H9 - B9) / Company_Data!H9) -> 0.39007143 | D9: =(Company_Data!C9 * Assumptions!$B$8)/1000 -> 16.8 | E9: =IF(C9 < 0.15, "LEADER", IF(C9 < 0.4, "STABLE", "AT RISK")) -> STABLE | F9: =IF(C9 < 0.15, "AAA", IF(C9 < 0.35, "BBB", "CCC")) -> CCC | G9: =IF(F9 = "AAA", "BUY", IF(F9 = "BBB", "HOLD", "SELL")) -> SELL
A10: =Company_Data!A10 -> Thyssenkrupp | B10: =Company_Data!H10 - Carbon_Risk_Engine!J10 -> 1.4264 | C10: =IF(B10 <= 0, "EBITDA Negative", (Company_Data!H10 - B10) / Company_Data!H10) -> 0.42944 | D10: =(Company_Data!C10 * Assumptions!$B$8)/1000 -> 6.6 | E10: =IF(C10 < 0.15, "LEADER", IF(C10 < 0.4, "STABLE", "AT RISK")) -> AT RISK | F10: =IF(C10 < 0.15, "AAA", IF(C10 < 0.35, "BBB", "CCC")) -> CCC | G10: =IF(F10 = "AAA", "BUY", IF(F10 = "BBB", "HOLD", "SELL")) -> SELL
A11: =Company_Data!A11 -> Voestalpine | B11: =Company_Data!H11 - Carbon_Risk_Engine!J11 -> 1.9172 | C11: =IF(B11 <= 0, "EBITDA Negative", (Company_Data!H11 - B11) / Company_Data!H11) -> 0.12854545 | D11: =(Company_Data!C11 * Assumptions!$B$8)/1000 -> 4.2 | E11: =IF(C11 < 0.15, "LEADER", IF(C11 < 0.4, "STABLE", "AT RISK")) -> LEADER | F11: =IF(C11 < 0.15, "AAA", IF(C11 < 0.35, "BBB", "CCC")) -> AAA | G11: =IF(F11 = "AAA", "BUY", IF(F11 = "BBB", "HOLD", "SELL")) -> BUY

Sheet Carbon_Risk_Engine
A1: Company | B1: Total Emission (Mt) | C1: Gross Carbon Cost ($M) | D1: Pass-through Benefit ($M) | E1: EU CBAM Liability ($B) | F1: Net Carbon Impact ($M) | G1: Domestic Carbon Cost ($B) | H1: Net Compliance Cost ($B) | I1: Carbon Mitigation ($B) | J1: Final Net Compliance Cost ($B)
A2: =Company_Data!A2 -> Nucor | B2: =Company_Data!C2 * Company_Data!F2 -> 10.75 | C2: =B2 * Assumptions!$B$2 -> 752.5 | D2: =C2 * Assumptions!$B$5 -> 301 | E2: =MAX(0, (Company_Data!F2 - Assumptions!$B$7) * Company_Data!I2 * Assumptions!$B$4) / 1000 -> 0 | F2: =(C2 - D2) + E2 -> 451.5 | G2: =(C2 - D2) / 1000 -> 0.4515 | H2: =E2 + G2 -> 0.4515 | I2: =C2/ 1000 * 0.4 -> 0.301 | J2: =H2 - I2 -> 0.1505
A3: =Company_Data!A3 -> Steel Dynamics | B3: =Company_Data!C3 * Company_Data!F3 -> 6.5 | C3: =B3 * Assumptions!$B$2 -> 455 | D3: =C3 * Assumptions!$B$5 -> 182 | E3: =MAX(0, (Company_Data!F3 - Assumptions!$B$7) * Company_Data!I3 * Assumptions!$B$4) / 1000 -> 0 | F3: =(C3 - D3) + E3 -> 273 | G3: =(C3 - D3) / 1000 -> 0.273 | H3: =E3 + G3 -> 0.273 | I3: =C3/ 1000 * 0.4 -> 0.182 | J3: =H3 - I3 -> 0.091
A4: =Company_Data!A4 -> ArcelorMittal | B4: =Company_Data!C4 * Company_Data!F4 -> 101.5 | C4: =B4 * Assumptions!$B$2 -> 7105 | D4: =C4 * Assumptions!$B$5 -> 2842 | E4: =MAX(0, (Company_Data!F4 - Assumptions!$B$7) * Company_Data!I4 * Assumptions!$B$4) / 1000 -> 0.4725 | F4: =(C4 - D4) + E4 -> 4263.4725 | G4: =(C4 - D4) / 1000 -> 4.263 | H4: =E4 + G4 -> 4.7355 | I4: =C4/ 1000 * 0.4 -> 2.842 | J4: =H4 - I4 -> 1.8935
A5: =Company_Data!A5 -> Baowu Steel | B5: =Company_Data!C5 * Company_Data!F5 -> 273 | C5: =B5 * Assumptions!$B$2 -> 19110 | D5: =C5 * Assumptions!$B$5 -> 7644 | E5: =MAX(0, (Company_Data!F5 - Assumptions!$B$7) * Company_Data!I5 * Assumptions!$B$4) / 1000 -> 0.63 | F5: =(C5 - D5) + E5 -> 11466.63 | G5: =(C5 - D5) / 1000 -> 11.466 | H5: =E5 + G5 -> 12.096 | I5: =C5/ 1000 * 0.4 -> 7.644 | J5: =H5 - I5 -> 4.452
A6: =Company_Data!A6 -> POSCO | B6: =Company_Data!C6 * Company_Data!F6 -> 81.9 | C6: =B6 * Assumptions!$B$2 -> 5733 | D6: =C6 * Assumptions!$B$5 -> 2293.2 | E6: =MAX(0, (Company_Data!F6 - Assumptions!$B$7) * Company_Data!I6 * Assumptions!$B$4) / 1000 -> 0.2475 | F6: =(C6 - D6) + E6 -> 3440.0475 | G6: =(C6 - D6) / 1000 -> 3.4398 | H6: =E6 + G6 -> 3.6873 | I6: =C6/ 1000 * 0.4 -> 2.2932 | J6: =H6 - I6 -> 1.3941
A7: =Company_Data!A7 -> Nippon Steel | B7: =Company_Data!C7 * Company_Data!F7 -> 90.2 | C7: =B7 * Assumptions!$B$2 -> 6314 | D7: =C7 * Assumptions!$B$5 -> 2525.6 | E7: =MAX(0, (Company_Data!F7 - Assumptions!$B$7) * Company_Data!I7 * Assumptions!$B$4) / 1000 -> 0.234 | F7: =(C7 - D7) + E7 -> 3788.634 | G7: =(C7 - D7) / 1000 -> 3.7884 | H7: =E7 + G7 -> 4.0224 | I7: =C7/ 1000 * 0.4 -> 2.5256 | J7: =H7 - I7 -> 1.4968
A8: =Company_Data!A8 -> Tata Steel | B8: =Company_Data!C8 * Company_Data!F8 -> 68.82 | C8: =B8 * Assumptions!$B$2 -> 4817.4 | D8: =C8 * Assumptions!$B$5 -> 1926.96 | E8: =MAX(0, (Company_Data!F8 - Assumptions!$B$7) * Company_Data!I8 * Assumptions!$B$4) / 1000 -> 0.2214 | F8: =(C8 - D8) + E8 -> 2890.6614 | G8: =(C8 - D8) / 1000 -> 2.89044 | H8: =E8 + G8 -> 3.11184 | I8: =C8/ 1000 * 0.4 -> 1.92696 | J8: =H8 - I8 -> 1.18488
A9: =Company_Data!A9 -> JSW Steel | B9: =Company_Data!C9 * Company_Data!F9 -> 65.8 | C9: =B9 * Assumptions!$B$2 -> 4606 | D9: =C9 * Assumptions!$B$5 -> 1842.4 | E9: =MAX(0, (Company_Data!F9 - Assumptions!$B$7) * Company_Data!I9 * Assumptions!$B$4) / 1000 -> 0.171 | F9: =(C9 - D9) + E9 -> 2763.771 | G9: =(C9 - D9) / 1000 -> 2.7636 | H9: =E9 + G9 -> 2.9346 | I9: =C9/ 1000 * 0.4 -> 1.8424 | J9: =H9 - I9 -> 1.0922
A10: =Company_Data!A10 -> Thyssenkrupp | B10: =Company_Data!C10 * Company_Data!F10 -> 23.65 | C10: =B10 * Assumptions!$B$2 -> 1655.5 | D10: =C10 * Assumptions!$B$5 -> 662.2 | E10: =MAX(0, (Company_Data!F10 - Assumptions!$B$7) * Company_Data!I10 * Assumptions!$B$4) / 1000 -> 0.7425 | F10: =(C10 - D10) + E10 -> 994.0425 | G10: =(C10 - D10) / 1000 -> 0.9933 | H10: =E10 + G10 -> 1.7358 | I10: =C10/ 1000 * 0.4 -> 0.6622 | J10: =H10 - I10 -> 1.0736
A11: =Company_Data!A11 -> Voestalpine | B11: =Company_Data!C11 * Company_Data!F11 -> 11.2 | C11: =B11 * Assumptions!$B$2 -> 784 | D11: =C11 * Assumptions!$B$5 -> 313.6 | E11: =MAX(0, (Company_Data!F11 - Assumptions!$B$7) * Company_Data!I11 * Assumptions!$B$4) / 1000 -> 0.126 | F11: =(C11 - D11) + E11 -> 470.526 | G11: =(C11 - D11) / 1000 -> 0.4704 | H11: =E11 + G11 -> 0.5964 | I11: =C11/ 1000 * 0.4 -> 0.3136 | J11: =H11 - I11 -> 0.2828

Sheet Company_Data
A1: Company | B1: Region | C1: Production (Mt) | D1: EAF Share % | E1: BF-BOF Share % | F1: Emission Intensity (tCO₂/t steel) | G1: Revenue ($B) | H1: Base EBITDA ($B) | I1: EU Exports (Mt)
A2: Nucor | B2: USA | C2: 25 | D2: 1 | E2: 0 | F2: 0.43 | G2: 35 | H2: 5.3 | I2: 0.5
A3: Steel Dynamics | B3: USA | C3: 13 | D3: 1 | E3: 0 | F3: 0.5 | G3: 18 | H3: 3.5 | I3: 0.2
A4: ArcelorMittal | B4: Europe/Global | C4: 58 | D4: 0.2 | E4: 0.8 | F4: 1.75 | G4: 68 | H4: 6.5 | I4: 15
A5: Baowu Steel | B5: China | C5: 130 | D5: 0.1 | E5: 0.9 | F5: 2.1 | G5: 150 | H5: 12 | I5: 10
A6: POSCO | B6: South Korea | C6: 42 | D6: 0.15 | E6: 0.85 | F6: 1.95 | G6: 60 | H6: 5.5 | I6: 5
A7: Nippon Steel | B7: Japan | C7: 44 | D7: 0.1 | E7: 0.9 | F7: 2.05 | G7: 55 | H7: 5 | I7: 4
A8: Tata Steel | B8: India | C8: 31 | D8: 0.1 | E8: 0.9 | F8: 2.22 | G8: 26 | H8: 3.1 | I8: 3
A9: JSW Steel | B9: India | C9: 28 | D9: 0.15 | E9: 0.85 | F9: 2.35 | G9: 22 | H9: 2.8 | I9: 2
A10: Thyssenkrupp | B10: Germany | C10: 11 | D10: 0.05 | E10: 0.95 | F10: 2.15 | G10: 40 | H10: 2.5 | I10: 11
A11: Voestalpine | B11: Austria | C11: 7 | D11: 0.1 | E11: 0.9 | F11: 1.6 | G11: 18 | H11: 2.2 | I11: 7

Sheet Assumptions
A1: Parameter | B1: Value | E1: Production Route | F1: Realistic Intensity Range | G1: Primary User Examples
A2: Base Carbon Price | B2: 70 | E2: Scrap-EAF | F2: 0.35 – 0.70 | G2: Nucor (0.43), Steel Dynamics
A3: Stress Carbon Price | B3: 100 | E3: DRI-EAF (Gas) | F3: 1.20 – 1.60 | G3: Cleveland-Cliffs (mixed), Midrex users
A4: EU Carbon Price | B4: 90 | E4: BF-BOF (Coal) | F4: 2.10 – 2.40 | G4: Tata Steel (2.22), Baowu (2.30)
A5: Cost Pass-Through | B5: 0.4 | E5: BF-BOF (EU) | F5: 1.70 – 1.95 | G5: ArcelorMittal (1.75), Thyssenkrupp
A6: Mitigation Rate (%) | B6: 0.1
A7: EU CBAM Benchmark | B7: 1.4
A8: Transition Capex | B8: 600
A9: CBAM Deadline | B9: 46112
